djangocms_time_wizard/__init__.py
djangocms_time_wizard/apps.py
djangocms_time_wizard/cms_plugins.py
djangocms_time_wizard/conf.py
djangocms_time_wizard/models.py
djangocms_time_wizard/migrations/0001_initial.py
djangocms_time_wizard/migrations/0002_timewizardinlinemodel.py
djangocms_time_wizard/migrations/__init__.py
djangocms_time_wizard/static/djangocms_time_wizard/css/djangocms_time_wizard.css
djangocms_time_wizard/static/djangocms_time_wizard/js/djangocms_time_wizard.js
djangocms_time_wizard/templates/djangocms_time_wizard/time_wizard.html
djangocms_time_wizard-2.4.1.dist-info/licenses/LICENSE
tests/__init__.py
tests/settings.py
tests/test_migrations.py
tests/test_models.py
djangocms_time_wizard-2.4.1.dist-info/METADATA
djangocms_time_wizard-2.4.1.dist-info/WHEEL
djangocms_time_wizard-2.4.1.dist-info/top_level.txt
djangocms_time_wizard-2.4.1.dist-info/RECORD
