Metadata-Version: 2.4
Name: djangocms-time-wizard
Version: 2.4.1
Summary: Simple plugin with django-time-wizard relation
Home-page: https://github.com/wfehr/djangocms-time-wizard
Download-URL: https://github.com/wfehr/djangocms-time-wizard/tarball/master
Author: Wolfgang Fehr
Author-email: dev@wfehr.de
Classifier: Environment :: Web Environment
Classifier: Framework :: Django
Classifier: Framework :: Django :: 3.2
Classifier: Framework :: Django :: 4.0
Classifier: Framework :: Django :: 4.1
Classifier: Framework :: Django :: 4.2
Classifier: Framework :: Django :: 5.0
Classifier: Framework :: Django :: 5.1
Classifier: Framework :: Django :: 5.2
Classifier: Framework :: Django CMS
Classifier: Framework :: Django CMS :: 3.7
Classifier: Framework :: Django CMS :: 3.8
Classifier: Framework :: Django CMS :: 3.9
Classifier: Framework :: Django CMS :: 3.10
Classifier: Framework :: Django CMS :: 3.11
Classifier: Framework :: Django CMS :: 4.1
Classifier: Framework :: Django CMS :: 5.0
Classifier: Intended Audience :: Developers
Classifier: License :: OSI Approved :: BSD License
Classifier: Operating System :: OS Independent
Classifier: Programming Language :: Python :: 3
Classifier: Programming Language :: Python :: 3.7
Classifier: Programming Language :: Python :: 3.8
Classifier: Programming Language :: Python :: 3.9
Classifier: Programming Language :: Python :: 3.10
Classifier: Programming Language :: Python :: 3.11
Classifier: Programming Language :: Python :: 3.12
Classifier: Topic :: Internet :: WWW/HTTP
Classifier: Topic :: Internet :: WWW/HTTP :: Dynamic Content
License-File: LICENSE
Requires-Dist: django-cms
Requires-Dist: django-time-wizard
Dynamic: author
Dynamic: author-email
Dynamic: classifier
Dynamic: description
Dynamic: download-url
Dynamic: home-page
Dynamic: license-file
Dynamic: requires-dist
Dynamic: summary
